oarepo_theme/__init__.py
oarepo_theme/webpack.py
oarepo_theme/assets/semantic-ui/less/theme.config
oarepo_theme/assets/semantic-ui/less/oarepo/theme.less
oarepo_theme/assets/semantic-ui/templates/custom_fields/.gitkeep
oarepo_theme-1.0.0.dev5.dist-info/METADATA
oarepo_theme-1.0.0.dev5.dist-info/WHEEL
oarepo_theme-1.0.0.dev5.dist-info/entry_points.txt
oarepo_theme-1.0.0.dev5.dist-info/licenses/LICENSE
oarepo_theme-1.0.0.dev5.dist-info/RECORD
