Metadata-Version: 2.4
Name: oarepo-theme
Version: 1.0.0.dev5
Summary: SemanticUI Invenio app theme overlay for NRP repositories
Project-URL: Documentation, https://github.com/oarepo/oarepo-theme#readme
Project-URL: Issues, https://github.com/oarepo/oarepo-theme/issues
Project-URL: Source, https://github.com/oarepo/oarepo-theme
Project-URL: Homepage, https://github.com/oarepo/oarepo-theme
Author-email: "CESNET a.l.e." <bauer@cesnet.cz>
License-Expression: MIT
License-File: LICENSE
Classifier: Development Status :: 4 - Beta
Classifier: Programming Language :: Python
Classifier: Programming Language :: Python :: 3.13
Classifier: Programming Language :: Python :: 3.14
Classifier: Programming Language :: Python :: Implementation :: CPython
Requires-Python: <3.15,>=3.13
Requires-Dist: oarepo[rdm,tests]<15,>=14
Provides-Extra: oarepo14
Requires-Dist: oarepo<15.0.0,>=14.0.0; extra == 'oarepo14'
Provides-Extra: tests
Requires-Dist: oarepo-runtime<3,>=2.0.0dev34; extra == 'tests'
